discord_base_bots/__init__.py
discord_base_bots/base.py
discord_base_bots/dice_bot.py
discord_base_bots/fighter.py
discord_base_bots-0.1.19.dist-info/METADATA
discord_base_bots-0.1.19.dist-info/WHEEL
discord_base_bots-0.1.19.dist-info/top_level.txt
discord_base_bots-0.1.19.dist-info/RECORD
