Metadata-Version: 2.1
Name: discord-base-bots
Version: 0.1.19
Summary: What bots are made of
Home-page: https://gitlab.com/LISTERINE/discord-base-bots
Author: jferretti
Author-email: jon@jonathanferretti.com
License: UNKNOWN
Platform: UNKNOWN
Classifier: Development Status :: 4 - Beta
Requires-Python: >=3.6
Requires-Dist: discord.py
Requires-Dist: python-dotenv
Requires-Dist: idna (==2.10)
